textprocessors/__init__.py
textprocessors/text_processor.py
textprocessors-0.0.4.dist-info/LICENSE
textprocessors-0.0.4.dist-info/METADATA
textprocessors-0.0.4.dist-info/WHEEL
textprocessors-0.0.4.dist-info/top_level.txt
textprocessors-0.0.4.dist-info/RECORD
