Metadata-Version: 2.1
Name: textprocessors
Version: 0.0.4
Summary: Allows easy clean up of text
Home-page: https://github.com/upshiftbe/processors
Author: Upshift
Author-email: contact@upshift.be
Project-URL: Bug Tracker, https://github.com/upshiftbe/processors/issues
Classifier: Programming Language :: Python :: 3
Classifier: License :: OSI Approved :: MIT License
Classifier: Operating System :: OS Independent
Requires-Python: >=3.6
License-File: LICENSE
Requires-Dist: demoji
